{"time":{"updated":"Dec 21, 2019 22:31:00 UTC","updatedISO":"2019-12-21T22:31:00+00:00","updateduk":"Dec 21, 2019 at 22:31 GMT"},"disclaimer":"This data was produced from the CoinDesk Bitcoin Price Index (USD). Non-USD currency data converted using hourly conversion rate from openexchangerates.org","chartName":"Bitcoin","bpi":{"USD":{"code":"USD","symbol":"&#36;","rate":"7,140.2167","description":"United States Dollar","rate_float":7140.2167},"GBP":{"code":"GBP","symbol":"&pound;","rate":"5,490.5767","description":"British Pound Sterling","rate_float":5490.5767},"EUR":{"code":"EUR","symbol":"&euro;","rate":"6,445.8663","description":"Euro","rate_float":6445.8663}}}